test_run/__init__.py
test_run/_main.py
test_run-0.0.24.dist-info/DESCRIPTION.rst
test_run-0.0.24.dist-info/METADATA
test_run-0.0.24.dist-info/RECORD
test_run-0.0.24.dist-info/WHEEL
test_run-0.0.24.dist-info/entry_points.txt
test_run-0.0.24.dist-info/metadata.json
test_run-0.0.24.dist-info/top_level.txt
